ironik/__init__.py
ironik/__main__.py
ironik/cli/__init__.py
ironik/cli/cli_helper.py
ironik/cli/ironik_cli.py
ironik/config_file_handler/__init__.py
ironik/config_file_handler/cloud_conf_parser.py
ironik/config_file_handler/deploy_template.py
ironik/config_file_handler/manifest_parser.py
ironik/manifests/cinder-csi-plugin.yaml
ironik/manifests/cloud-controller-manager-role-bindings.yaml
ironik/manifests/cloud-controller-manager-roles.yaml
ironik/manifests/openstack-cloud-controller-manager-ds.yaml
ironik/openstack_handler/__init__.py
ironik/openstack_handler/openstack_api_caller.py
ironik/openstack_handler/resource_calculator.py
ironik/py.typed
ironik/rancher/__init__.py
ironik/rancher/kubernetes_api_caller.py
ironik/rancher/rancher_api_caller.py
ironik/util/__init__.py
ironik/util/exceptions.py
ironik/util/ironik_logger.py
ironik-0.1.8.dist-info/LICENSE
ironik-0.1.8.dist-info/METADATA
ironik-0.1.8.dist-info/WHEEL
ironik-0.1.8.dist-info/entry_points.txt
ironik-0.1.8.dist-info/RECORD
