Metadata-Version: 2.1
Name: ironik
Version: 0.1.8
Summary: In Rancher Openstack; Now Install Kubernetes (Ironik); Python CLI Tool for deploying Kubernetes on OpenStack via Rancher.
Home-page: https://gitlab.gwdg.de/jonathan.decker1/ironik
License: MIT
Author: Jonathan Decker
Author-email: jonathan.decker@uni-goettingen.de
Requires-Python: >=3.9,<4.0
Classifier: License :: OSI Approved :: MIT License
Classifier: Programming Language :: Python :: 3
Classifier: Programming Language :: Python :: 3.9
Classifier: Programming Language :: Python :: 3.10
Classifier: Programming Language :: Python :: 3.11
Classifier: Programming Language :: Python :: 3.10
Classifier: Programming Language :: Python :: 3.11
Classifier: Programming Language :: Python :: 3.9
Requires-Dist: cerberus (>=1.3.5,<2.0.0)
Requires-Dist: click (>=8.1.7,<9.0.0)
Requires-Dist: jinja2 (>=3.1.3,<4.0.0)
Requires-Dist: kubernetes (>=29.0.0,<30.0.0)
Requires-Dist: openstacksdk (>=2.1.0,<3.0.0)
Requires-Dist: pyyaml (>=6.0.1,<7.0.0)
Requires-Dist: rich (>=13.7.0,<14.0.0)
Project-URL: Documentation, https://ironik.readthedocs.io
Project-URL: Repository, https://gitlab.gwdg.de/jonathan.decker1/ironik
